Workbook

Sheet 前提条件
A1: NGT ウォークツアー 価格モデル｜前提条件
A2: 凡例：青字＝入力値（変更可）／黄色塗り＝推測値のため要確認／黒字＝計算式。前提を変えると全シートが再計算されます。
A3: 最終更新：2026-10-02（手数料・システム利用料を LINKTIVITY 取引明細 2026/9 の実数に更新、ハンコの費用なしを反映、9月実績シートを追加）
A4: 項目 | B4: 値 | C4: 単位 | D4: 出典・備考
A5: ガイド費（特別単価）
A6: 参加者3名まで（2時間） | B6: 4500 | C6: 円/回 | D6: Reelu 伊藤様提示・最初の6ヶ月の特別単価（手数料込）
A7: 参加者4〜6名（2時間） | B7: 6000 | C7: 円/回 | D7: 同上
A8: 参加者7名以上（2時間） | B8: 8000 | C8: 円/回 | D8: 同上
A9: ガイド費（通常単価・7ヶ月目以降）【参考：計算の基準は特別単価】
A10: 基本料金（2時間・3名まで） | B10: 7980 | C10: 円/回 | D10: Reelu 通常：2時間7,980円（税込）
A11: 4名目以降の加算率（1名ごと） | B11: 0.05 | C11: 率 | D11: 「4名以上は時給×5%ずつ追加」を「1名増えるごとに+5%」と解釈（推測・要確認）
A12: その他の催行コスト
A13: ガイド交通費 | B13: 1000 | C13: 円/回 | D13: 実費精算。1回あたりの平均値は推測・要確認
A14: 公式直販のシステム利用料率 | B14: 0.07 | C14: 率 | D14: 実数：LINKTIVITY取引明細（2026/9）。総額に対して7%（決済込み）
A15: 目標利益率（催行1回あたり） | B15: 0.25 | C15: 率 | D15: 広告費・運営費を賄うための粗利目標（提案値）
A16: 現行価格（参考）
A17: 現行 公式価格（1名あたり） | B17: 2500 | C17: 円/人 | D17: 実数：LINKTIVITY取引明細（2026/9）の公式直販の単価
A18: 現行 OTA価格（1名あたり） | B18: 3000 | C18: 円/人 | D18: 実数：LINKTIVITY取引明細（2026/9）。Klook・Travelers Road とも1名¥3,000
A19: ハンコツアーの催行コスト（ガイド費・材料費） | B19: 0 | C19: 円/回 | D19: ご本人確認 2026-10-02：費用はかからない
A20: チャネル別の手数料
A22: Viator | B22: 0.25 | C22: 率 | D22: 業界一般値の仮置き（推測）。LINKTIVITY経由の実際の契約料率に差し替え
A23: GetYourGuide | B23: 0.25 | C23: 率 | D23: 業界一般値の仮置き（推測）。LINKTIVITY経由の実際の契約料率に差し替え
A24: Klook | B24: 0.2 | C24: 率 | D24: 実数：LINKTIVITY取引明細（2026/9）
A25: KKday | B25: 0.2 | C25: 率 | D25: 業界一般値の仮置き（推測）。LINKTIVITY経由の実際の契約料率に差し替え
A26: VELTRA | B26: 0.2 | C26: 率 | D26: 業界一般値の仮置き（推測）。LINKTIVITY経由の実際の契約料率に差し替え
A27: Travelers Road（卸） | B27: 0.17 | C27: 率 | D27: 実数：LINKTIVITY取引明細（2026/9）
A28: Private Group | B28: 0.17 | C28: 率 | D28: 実数：LINKTIVITY取引明細（2026/9）
A29: OTA経由のシステム利用料率 | B29: 0.03 | C29: 率 | D29: 実数：LINKTIVITY取引明細（2026/9）。OTA手数料とは別に総額の3%。キャンセル時に戻る条件は要確認

Sheet 公式価格（段階制）
A1: 公式サイト価格（大人1名あたり・人数による段階制）と催行1回あたりの収支
A2: B5〜B8（青字）が提案価格。1名／2名／3名／4名以上の4段階で、4名以上は同額。利益の計算はReelu特別単価（現状の単価）が基準。通常単価の列は特別単価終了後の参考。
A4: 予約人数（大人） | B4: 1名あたり価格 | C4: 予約総額 | D4: 決済手数料 | E4: ガイド費（特別単価） | F4: 交通費 | G4: 利益（特別単価） | H4: 利益率（特別） | I4: ガイド費（通常単価）【参考】 | J4: 利益（通常単価）【参考】 | K4: 利益率（通常）【参考】 | L4: 目標利益率に必要な1名単価（特別） | M4: 目標利益率に必要な1名単価（通常）【参考】
A5: 1 | B5: 8000 | C5: =A5*B5 | D5: =C5*前提条件!$B$14 | E5: =IF(A5<=3,前提条件!$B$6,IF(A5<=6,前提条件!$B$7,前提条件!$B$8)) | F5: =前提条件!$B$13 | G5: =C5-D5-E5-F5 | H5: =IF(C5=0,0,G5/C5) | I5: =前提条件!$B$10*(1+前提条件!$B$11*MAX(0,A5-3)) | J5: =C5-D5-I5-F5 | K5: =IF(C5=0,0,J5/C5) | L5: =ROUNDUP((E5+F5)/(A5*(1-前提条件!$B$14-前提条件!$B$15)),-2) | M5: =ROUNDUP((I5+F5)/(A5*(1-前提条件!$B$14-前提条件!$B$15)),-2)
A6: 2 | B6: 4000 | C6: =A6*B6 | D6: =C6*前提条件!$B$14 | E6: =IF(A6<=3,前提条件!$B$6,IF(A6<=6,前提条件!$B$7,前提条件!$B$8)) | F6: =前提条件!$B$13 | G6: =C6-D6-E6-F6 | H6: =IF(C6=0,0,G6/C6) | I6: =前提条件!$B$10*(1+前提条件!$B$11*MAX(0,A6-3)) | J6: =C6-D6-I6-F6 | K6: =IF(C6=0,0,J6/C6) | L6: =ROUNDUP((E6+F6)/(A6*(1-前提条件!$B$14-前提条件!$B$15)),-2) | M6: =ROUNDUP((I6+F6)/(A6*(1-前提条件!$B$14-前提条件!$B$15)),-2)
A7: 3 | B7: 2800 | C7: =A7*B7 | D7: =C7*前提条件!$B$14 | E7: =IF(A7<=3,前提条件!$B$6,IF(A7<=6,前提条件!$B$7,前提条件!$B$8)) | F7: =前提条件!$B$13 | G7: =C7-D7-E7-F7 | H7: =IF(C7=0,0,G7/C7) | I7: =前提条件!$B$10*(1+前提条件!$B$11*MAX(0,A7-3)) | J7: =C7-D7-I7-F7 | K7: =IF(C7=0,0,J7/C7) | L7: =ROUNDUP((E7+F7)/(A7*(1-前提条件!$B$14-前提条件!$B$15)),-2) | M7: =ROUNDUP((I7+F7)/(A7*(1-前提条件!$B$14-前提条件!$B$15)),-2)
A8: 4 | B8: 2500 | C8: =A8*B8 | D8: =C8*前提条件!$B$14 | E8: =IF(A8<=3,前提条件!$B$6,IF(A8<=6,前提条件!$B$7,前提条件!$B$8)) | F8: =前提条件!$B$13 | G8: =C8-D8-E8-F8 | H8: =IF(C8=0,0,G8/C8) | I8: =前提条件!$B$10*(1+前提条件!$B$11*MAX(0,A8-3)) | J8: =C8-D8-I8-F8 | K8: =IF(C8=0,0,J8/C8) | L8: =ROUNDUP((E8+F8)/(A8*(1-前提条件!$B$14-前提条件!$B$15)),-2) | M8: =ROUNDUP((I8+F8)/(A8*(1-前提条件!$B$14-前提条件!$B$15)),-2)
A9: 5 | B9: =$B$8 | C9: =A9*B9 | D9: =C9*前提条件!$B$14 | E9: =IF(A9<=3,前提条件!$B$6,IF(A9<=6,前提条件!$B$7,前提条件!$B$8)) | F9: =前提条件!$B$13 | G9: =C9-D9-E9-F9 | H9: =IF(C9=0,0,G9/C9) | I9: =前提条件!$B$10*(1+前提条件!$B$11*MAX(0,A9-3)) | J9: =C9-D9-I9-F9 | K9: =IF(C9=0,0,J9/C9) | L9: =ROUNDUP((E9+F9)/(A9*(1-前提条件!$B$14-前提条件!$B$15)),-2) | M9: =ROUNDUP((I9+F9)/(A9*(1-前提条件!$B$14-前提条件!$B$15)),-2)
A10: 6 | B10: =$B$8 | C10: =A10*B10 | D10: =C10*前提条件!$B$14 | E10: =IF(A10<=3,前提条件!$B$6,IF(A10<=6,前提条件!$B$7,前提条件!$B$8)) | F10: =前提条件!$B$13 | G10: =C10-D10-E10-F10 | H10: =IF(C10=0,0,G10/C10) | I10: =前提条件!$B$10*(1+前提条件!$B$11*MAX(0,A10-3)) | J10: =C10-D10-I10-F10 | K10: =IF(C10=0,0,J10/C10) | L10: =ROUNDUP((E10+F10)/(A10*(1-前提条件!$B$14-前提条件!$B$15)),-2) | M10: =ROUNDUP((I10+F10)/(A10*(1-前提条件!$B$14-前提条件!$B$15)),-2)
A11: 7 | B11: =$B$8 | C11: =A11*B11 | D11: =C11*前提条件!$B$14 | E11: =IF(A11<=3,前提条件!$B$6,IF(A11<=6,前提条件!$B$7,前提条件!$B$8)) | F11: =前提条件!$B$13 | G11: =C11-D11-E11-F11 | H11: =IF(C11=0,0,G11/C11) | I11: =前提条件!$B$10*(1+前提条件!$B$11*MAX(0,A11-3)) | J11: =C11-D11-I11-F11 | K11: =IF(C11=0,0,J11/C11) | L11: =ROUNDUP((E11+F11)/(A11*(1-前提条件!$B$14-前提条件!$B$15)),-2) | M11: =ROUNDUP((I11+F11)/(A11*(1-前提条件!$B$14-前提条件!$B$15)),-2)
A12: 8 | B12: =$B$8 | C12: =A12*B12 | D12: =C12*前提条件!$B$14 | E12: =IF(A12<=3,前提条件!$B$6,IF(A12<=6,前提条件!$B$7,前提条件!$B$8)) | F12: =前提条件!$B$13 | G12: =C12-D12-E12-F12 | H12: =IF(C12=0,0,G12/C12) | I12: =前提条件!$B$10*(1+前提条件!$B$11*MAX(0,A12-3)) | J12: =C12-D12-I12-F12 | K12: =IF(C12=0,0,J12/C12) | L12: =ROUNDUP((E12+F12)/(A12*(1-前提条件!$B$14-前提条件!$B$15)),-2) | M12: =ROUNDUP((I12+F12)/(A12*(1-前提条件!$B$14-前提条件!$B$15)),-2)
A13: 9 | B13: =$B$8 | C13: =A13*B13 | D13: =C13*前提条件!$B$14 | E13: =IF(A13<=3,前提条件!$B$6,IF(A13<=6,前提条件!$B$7,前提条件!$B$8)) | F13: =前提条件!$B$13 | G13: =C13-D13-E13-F13 | H13: =IF(C13=0,0,G13/C13) | I13: =前提条件!$B$10*(1+前提条件!$B$11*MAX(0,A13-3)) | J13: =C13-D13-I13-F13 | K13: =IF(C13=0,0,J13/C13) | L13: =ROUNDUP((E13+F13)/(A13*(1-前提条件!$B$14-前提条件!$B$15)),-2) | M13: =ROUNDUP((I13+F13)/(A13*(1-前提条件!$B$14-前提条件!$B$15)),-2)
A14: 10 | B14: =$B$8 | C14: =A14*B14 | D14: =C14*前提条件!$B$14 | E14: =IF(A14<=3,前提条件!$B$6,IF(A14<=6,前提条件!$B$7,前提条件!$B$8)) | F14: =前提条件!$B$13 | G14: =C14-D14-E14-F14 | H14: =IF(C14=0,0,G14/C14) | I14: =前提条件!$B$10*(1+前提条件!$B$11*MAX(0,A14-3)) | J14: =C14-D14-I14-F14 | K14: =IF(C14=0,0,J14/C14) | L14: =ROUNDUP((E14+F14)/(A14*(1-前提条件!$B$14-前提条件!$B$15)),-2) | M14: =ROUNDUP((I14+F14)/(A14*(1-前提条件!$B$14-前提条件!$B$15)),-2)
A16: 読み方
A17: ・G列：Reelu特別単価（最初の6ヶ月）での催行1回あたり利益。全人数で黒字になるよう設計。
A18: ・J列：通常単価に戻った場合の利益。1〜3名は赤字になるため、特別単価の終了前に価格改定またはReeluとの単価交渉が必要。
A19: ・L列・M列：前提条件の目標利益率を満たすために必要な最低単価（100円単位で切り上げ）。価格を決める際の下限の目安。
A20: ・12歳以下：何人でも無料（大人の同伴が必要、2026-09-25確定）。子どもがガイド費の人数区分に数えられる場合は、その分だけ利益が下振れする。
A21: ・1回の催行＝1予約を前提に計算（実績では52予約中50予約が単独催行）。同じ枠に別予約が相乗りした分は上振れ要因。
A22: ・ハンコ代・スイーツ代などツアー固有の材料費は含まない。ハンコツアーは費用がかからないため段階制の対象外（「OTA価格」シートの一律行）。

Sheet OTA価格
A1: OTA販売価格（公式価格にOTA手数料を上乗せ）
A2: 計算式：OTA価格 ＝ 公式価格 ×（1 − 公式直販のシステム利用料率）÷（1 − OTA手数料率 − OTA経由のシステム利用料率）を100円単位で切り上げ。どのチャネルで売れても手取りが公式と同じになる（2026-10-02 実数で改定）。
A4: 予約人数（大人） | B4: 公式 1名あたり | C4: Viator | D4: GetYourGuide | E4: Klook | F4: KKday | G4: VELTRA | H4: Travelers Road（卸）
A5: 1名 | B5: ='公式価格（段階制）'!B5 | C5: =ROUNDUP($B5*(1-前提条件!$B$14)/(1-前提条件!$B$22-前提条件!$B$29),-2) | D5: =ROUNDUP($B5*(1-前提条件!$B$14)/(1-前提条件!$B$23-前提条件!$B$29),-2) | E5: =ROUNDUP($B5*(1-前提条件!$B$14)/(1-前提条件!$B$24-前提条件!$B$29),-2) | F5: =ROUNDUP($B5*(1-前提条件!$B$14)/(1-前提条件!$B$25-前提条件!$B$29),-2) | G5: =ROUNDUP($B5*(1-前提条件!$B$14)/(1-前提条件!$B$26-前提条件!$B$29),-2) | H5: =ROUNDUP($B5*(1-前提条件!$B$14)/(1-前提条件!$B$27-前提条件!$B$29),-2)
A6: 2名 | B6: ='公式価格（段階制）'!B6 | C6: =ROUNDUP($B6*(1-前提条件!$B$14)/(1-前提条件!$B$22-前提条件!$B$29),-2) | D6: =ROUNDUP($B6*(1-前提条件!$B$14)/(1-前提条件!$B$23-前提条件!$B$29),-2) | E6: =ROUNDUP($B6*(1-前提条件!$B$14)/(1-前提条件!$B$24-前提条件!$B$29),-2) | F6: =ROUNDUP($B6*(1-前提条件!$B$14)/(1-前提条件!$B$25-前提条件!$B$29),-2) | G6: =ROUNDUP($B6*(1-前提条件!$B$14)/(1-前提条件!$B$26-前提条件!$B$29),-2) | H6: =ROUNDUP($B6*(1-前提条件!$B$14)/(1-前提条件!$B$27-前提条件!$B$29),-2)
A7: 3名 | B7: ='公式価格（段階制）'!B7 | C7: =ROUNDUP($B7*(1-前提条件!$B$14)/(1-前提条件!$B$22-前提条件!$B$29),-2) | D7: =ROUNDUP($B7*(1-前提条件!$B$14)/(1-前提条件!$B$23-前提条件!$B$29),-2) | E7: =ROUNDUP($B7*(1-前提条件!$B$14)/(1-前提条件!$B$24-前提条件!$B$29),-2) | F7: =ROUNDUP($B7*(1-前提条件!$B$14)/(1-前提条件!$B$25-前提条件!$B$29),-2) | G7: =ROUNDUP($B7*(1-前提条件!$B$14)/(1-前提条件!$B$26-前提条件!$B$29),-2) | H7: =ROUNDUP($B7*(1-前提条件!$B$14)/(1-前提条件!$B$27-前提条件!$B$29),-2)
A8: 4名以上 | B8: ='公式価格（段階制）'!B8 | C8: =ROUNDUP($B8*(1-前提条件!$B$14)/(1-前提条件!$B$22-前提条件!$B$29),-2) | D8: =ROUNDUP($B8*(1-前提条件!$B$14)/(1-前提条件!$B$23-前提条件!$B$29),-2) | E8: =ROUNDUP($B8*(1-前提条件!$B$14)/(1-前提条件!$B$24-前提条件!$B$29),-2) | F8: =ROUNDUP($B8*(1-前提条件!$B$14)/(1-前提条件!$B$25-前提条件!$B$29),-2) | G8: =ROUNDUP($B8*(1-前提条件!$B$14)/(1-前提条件!$B$26-前提条件!$B$29),-2) | H8: =ROUNDUP($B8*(1-前提条件!$B$14)/(1-前提条件!$B$27-前提条件!$B$29),-2)
A9: ハンコ（一律） | B9: 2500 | C9: 3000 | D9: 3000 | E9: 3000 | F9: 3000 | G9: 3000 | H9: 3000
A10: 注記
A11: ・OTAによっては人数別の段階料金を設定できない場合がある。その場合はLINKTIVITY上で「1名プラン」「2名プラン」など人数別プランに分けて登録する（要LINKTIVITY確認）。
A12: ・Travelers Road（卸）は卸値契約のため、上乗せではなく卸値（ネット価格）で合意する形になる可能性が高い（要確認）。
A13: ・ハンコは費用がかからないため人数に関わらず一律（青字＝入力値）。OTAは売れている¥3,000を維持（Klookの式の値¥3,100との差は1名15円）。

Sheet 現行価格の収支
A1: 参考：現行価格（一律）で催行した場合の収支（ウォークツアー実績ベース）
A2: 出典：LINKTIVITY予約CSV（購入日 2025/9/1〜2026/9/24）のウォークツアー確定予約52件・催行51回を参加人数別に集計。
A4: 催行人数 | B4: 催行回数（実績） | C4: 現行公式価格での売上 | D4: ガイド費（特別） | E4: 交通費 | F4: 決済手数料 | G4: 1回あたり利益 | H4: 利益合計（回数×利益） | I4: 新価格での1回の利益 | J4: 新価格での利益合計
A5: 1 | B5: 17 | C5: =A5*前提条件!$B$17 | D5: =IF(A5<=3,前提条件!$B$6,IF(A5<=6,前提条件!$B$7,前提条件!$B$8)) | E5: =前提条件!$B$13 | F5: =C5*前提条件!$B$14 | G5: =C5-D5-E5-F5 | H5: =B5*G5 | I5: =INDEX('公式価格（段階制）'!$G$5:$G$14,A5) | J5: =B5*I5
A6: 2 | B6: 17 | C6: =A6*前提条件!$B$17 | D6: =IF(A6<=3,前提条件!$B$6,IF(A6<=6,前提条件!$B$7,前提条件!$B$8)) | E6: =前提条件!$B$13 | F6: =C6*前提条件!$B$14 | G6: =C6-D6-E6-F6 | H6: =B6*G6 | I6: =INDEX('公式価格（段階制）'!$G$5:$G$14,A6) | J6: =B6*I6
A7: 3 | B7: 9 | C7: =A7*前提条件!$B$17 | D7: =IF(A7<=3,前提条件!$B$6,IF(A7<=6,前提条件!$B$7,前提条件!$B$8)) | E7: =前提条件!$B$13 | F7: =C7*前提条件!$B$14 | G7: =C7-D7-E7-F7 | H7: =B7*G7 | I7: =INDEX('公式価格（段階制）'!$G$5:$G$14,A7) | J7: =B7*I7
A8: 4 | B8: 4 | C8: =A8*前提条件!$B$17 | D8: =IF(A8<=3,前提条件!$B$6,IF(A8<=6,前提条件!$B$7,前提条件!$B$8)) | E8: =前提条件!$B$13 | F8: =C8*前提条件!$B$14 | G8: =C8-D8-E8-F8 | H8: =B8*G8 | I8: =INDEX('公式価格（段階制）'!$G$5:$G$14,A8) | J8: =B8*I8
A9: 5 | B9: 3 | C9: =A9*前提条件!$B$17 | D9: =IF(A9<=3,前提条件!$B$6,IF(A9<=6,前提条件!$B$7,前提条件!$B$8)) | E9: =前提条件!$B$13 | F9: =C9*前提条件!$B$14 | G9: =C9-D9-E9-F9 | H9: =B9*G9 | I9: =INDEX('公式価格（段階制）'!$G$5:$G$14,A9) | J9: =B9*I9
A10: 7 | B10: 1 | C10: =A10*前提条件!$B$17 | D10: =IF(A10<=3,前提条件!$B$6,IF(A10<=6,前提条件!$B$7,前提条件!$B$8)) | E10: =前提条件!$B$13 | F10: =C10*前提条件!$B$14 | G10: =C10-D10-E10-F10 | H10: =B10*G10 | I10: =INDEX('公式価格（段階制）'!$G$5:$G$14,A10) | J10: =B10*I10
A11: 合計 | B11: =SUM(B5:B10) | H11: =SUM(H5:H10) | J11: =SUM(J5:J10)
A12: 赤字催行の回数 | B12: =SUMIF(G5:G10,"<0",B5:B10)
A14: ・全件を公式価格（¥2,500）で計算した試算。OTA経由分は手取りがさらに低い（Klook 77%・Travelers Road 80%、公式直販 93%）。ガイド費は特別単価を当てはめた仮定で、過去の実際のガイド費とは異なる。ハンコツアー（費用なし）も同じガイド費で計算しているため、赤字回数は実際より多く出ている。
A15: ・子ども（12歳以下無料）はCSVに人数が記録されていないため含まない。

Sheet 9月実績（チャネル別）
A1: 2026年9月の実績（購入日 9/1〜9/30）：チャネル×人数別の手取りと利益、新価格での試算
A2: 出典：LINKTIVITY 予約一覧・取引明細（集計値のみ。個人情報は含めない）。テスト予約1件・旅行者キャンセル3件は除外。1予約＝1催行と仮定。新価格の列は同じ予約が同じ件数入った場合の試算（推測）。
A4: チャネル | B4: ツアー | C4: 人数（大人） | D4: 予約数 | E4: 現行単価 | F4: OTA手数料率 | G4: システム利用料率 | H4: 手取り率 | I4: 現行の手取り | J4: 催行コスト | K4: 現行の利益 | L4: 新単価 | M4: 新価格の手取り | N4: 新価格の利益
A5: Klook | B5: ハンコ | C5: 1 | D5: 6 | E5: 3000 | F5: =前提条件!$B$24 | G5: =前提条件!$B$29 | H5: =1-F5-G5 | I5: =E5*C5*D5*H5 | J5: =前提条件!$B$19*D5 | K5: =I5-J5 | L5: ='OTA価格'!$E$9 | M5: =L5*C5*D5*H5 | N5: =M5-J5
A6: Klook | B6: ハンコ | C6: 2 | D6: 7 | E6: 3000 | F6: =前提条件!$B$24 | G6: =前提条件!$B$29 | H6: =1-F6-G6 | I6: =E6*C6*D6*H6 | J6: =前提条件!$B$19*D6 | K6: =I6-J6 | L6: ='OTA価格'!$E$9 | M6: =L6*C6*D6*H6 | N6: =M6-J6
A7: Klook | B7: ハンコ | C7: 4 | D7: 1 | E7: 3000 | F7: =前提条件!$B$24 | G7: =前提条件!$B$29 | H7: =1-F7-G7 | I7: =E7*C7*D7*H7 | J7: =前提条件!$B$19*D7 | K7: =I7-J7 | L7: ='OTA価格'!$E$9 | M7: =L7*C7*D7*H7 | N7: =M7-J7
A8: Travelers Road | B8: 秘境神社 | C8: 2 | D8: 1 | E8: 3000 | F8: =前提条件!$B$27 | G8: =前提条件!$B$29 | H8: =1-F8-G8 | I8: =E8*C8*D8*H8 | J8: =(IF(C8<=3,前提条件!$B$6,IF(C8<=6,前提条件!$B$7,前提条件!$B$8))+前提条件!$B$13)*D8 | K8: =I8-J8 | L8: =INDEX('OTA価格'!$H$5:$H$8,MIN(C8,4)) | M8: =L8*C8*D8*H8 | N8: =M8-J8
A9: Travelers Road | B9: 秘境神社 | C9: 3 | D9: 2 | E9: 3000 | F9: =前提条件!$B$27 | G9: =前提条件!$B$29 | H9: =1-F9-G9 | I9: =E9*C9*D9*H9 | J9: =(IF(C9<=3,前提条件!$B$6,IF(C9<=6,前提条件!$B$7,前提条件!$B$8))+前提条件!$B$13)*D9 | K9: =I9-J9 | L9: =INDEX('OTA価格'!$H$5:$H$8,MIN(C9,4)) | M9: =L9*C9*D9*H9 | N9: =M9-J9
A10: Travelers Road | B10: 秘境神社 | C10: 5 | D10: 1 | E10: 3000 | F10: =前提条件!$B$27 | G10: =前提条件!$B$29 | H10: =1-F10-G10 | I10: =E10*C10*D10*H10 | J10: =(IF(C10<=3,前提条件!$B$6,IF(C10<=6,前提条件!$B$7,前提条件!$B$8))+前提条件!$B$13)*D10 | K10: =I10-J10 | L10: =INDEX('OTA価格'!$H$5:$H$8,MIN(C10,4)) | M10: =L10*C10*D10*H10 | N10: =M10-J10
A11: 公式直販 | B11: 二丁目 | C11: 1 | D11: 1 | E11: 2500 | F11: 0 | G11: =前提条件!$B$14 | H11: =1-F11-G11 | I11: =E11*C11*D11*H11 | J11: =(IF(C11<=3,前提条件!$B$6,IF(C11<=6,前提条件!$B$7,前提条件!$B$8))+前提条件!$B$13)*D11 | K11: =I11-J11 | L11: =INDEX('公式価格（段階制）'!$B$5:$B$8,MIN(C11,4)) | M11: =L11*C11*D11*H11 | N11: =M11-J11
A12: 合計 | C12: =SUMPRODUCT(C5:C11,D5:D11) | D12: =SUM(D5:D11) | I12: =SUM(I5:I11) | J12: =SUM(J5:J11) | K12: =SUM(K5:K11) | M12: =SUM(M5:M11) | N12: =SUM(N5:N11)
A13: キャンセルで戻らなかったシステム利用料 | K13: -630
A15: 読み方
A16: ・利益の大半はKlook経由のハンコ（費用なし）。Reeluが案内するツアーは現行の一律価格だと1〜2名で赤字、段階制なら全人数で黒字。
A17: ・新価格の列は需要が変わらない前提の試算。値上げで予約数が減る影響は含まない（推測）。
